Lab1/LEDdecoder.v

module LEDdecoder (input [3:0] char, output [6:0] LED);
    reg [6:0] LED;
    
    always @(char) begin
        case (char)
            4'b0000: LED = 7'b0000000; // 0:
            4'b0001: LED = 7'b0110000; // 1:
            4'b0010: LED = 7'b1101101; // 2:
            4'b0011: LED = 7'b1111001; // 3:
            4'b0100: LED = 7'b0110011; // 4:
            4'b0101: LED = 7'b1011011; // 5:
            4'b0110: LED = 7'b1011111; // 6:
            4'b0111: LED = 7'b1110000; // 7:
            4'b1000: LED = 7'b1111111; // 8:
            4'b1001: LED = 7'b1111011; // 9:
            4'b1010: LED = 7'b1110111; // A:
            4'b1011: LED = 7'b0011111; // b:
            4'b1100: LED = 7'b1001110; // C:
            4'b1101: LED = 7'b0111101; // d:
            4'b1110: LED = 7'b1001111; // E:
            4'b1111: LED = 7'b1000111; // F:
        endcase
    end
endmodule

Lab1/testbench.v

module tb_;
    reg [3:0] char;
    wire [6:0] LED;

    LEDdecoder LEDdecoder_ (.char(char), .LED(LED));

    initial begin
        char = 4'b0000;
        #10 char = 4'b0001;
        #10 char = 4'b0010;
        #10 char = 4'b0011;
        #10 char = 4'b0100;
        #10 char = 4'b0101;
        #10 char = 4'b0110;
        #10 char = 4'b0111;
        #10 char = 4'b1000;
        #10 char = 4'b1001;
        #10 char = 4'b1010;
        #10 char = 4'b1011;
        #10 char = 4'b1100;
        #10 char = 4'b1101;
        #10 char = 4'b1110;
        #10 char = 4'b1111;
        #10 $finish;
    end
endmodule

Lab1/project_1/project_1.sim/sim_1/behav/xsim/tb_.vcd
$date
   Mon Oct  7 15:25:11 2024
$end
$version
  2018.3
$end
$timescale
  1ps
$end
$scope module tb_ $end
$var reg 4 ! char [3:0] $end
$var wire 7 " LED [6:0] $end
$scope module LEDdecoder_ $end
$var wire 4 # char [3:0] $end
$var reg 7 $ LED [6:0] $end
$upscope $end
$upscope $end
$enddefinitions $end
#0
$dumpvars
b0 !
b0 "
b0 #
b0 $
$end
#10000
b1 !
b110000 "
b1 #
b110000 $
#20000
b10 !
b1101101 "
b10 #
b1101101 $
#30000
b11 !
b1111001 "
b11 #
b1111001 $
#40000
b100 !
b110011 "
b100 #
b110011 $
#50000
b101 !
b1011011 "
b101 #
b1011011 $
#60000
b110 !
b1011111 "
b110 #
b1011111 $
#70000
b111 !
b1110000 "
b111 #
b1110000 $
#80000
b1000 !
b1111111 "
b1000 #
b1111111 $
#90000
b1001 !
b1111011 "
b1001 #
b1111011 $
#100000
b1010 !
b1110111 "
b1010 #
b1110111 $
#110000
b1011 !
b11111 "
b1011 #
b11111 $
#120000
b1100 !
b1001110 "
b1100 #
b1001110 $
#130000
b1101 !
b111101 "
b1101 #
b111101 $
#140000
b1110 !
b1001111 "
b1110 #
b1001111 $
#150000
b1111 !
b1000111 "
b1111 #
b1000111 $
#160000
b0 !
b0 "
b0 #
b0 $
#170000
b1 !
b110000 "
b1 #
b110000 $
#180000
b10 !
b1101101 "
b10 #
b1101101 $
#190000
b11 !
b1111001 "
b11 #
b1111001 $
#200000
b100 !
b110011 "
b100 #
b110011 $
#210000
b101 !
b1011011 "
b101 #
b1011011 $
#220000
b110 !
b1011111 "
b110 #
b1011111 $
#230000
b111 !
b1110000 "
b111 #
b1110000 $
#240000
b1000 !
b1111111 "
b1000 #
b1111111 $
#250000
b1001 !
b1111011 "
b1001 #
b1111011 $
#260000
b1010 !
b1110111 "
b1010 #
b1110111 $
#270000
b1011 !
b11111 "
b1011 #
b11111 $
#280000
b1100 !
b1001110 "
b1100 #
b1001110 $
#290000
b1101 !
b111101 "
b1101 #
b111101 $
#300000
b1110 !
b1001111 "
b1110 #
b1001111 $
#310000
b1111 !
b1000111 "
b1111 #
b1000111 $
#320000
b0 !
b0 "
b0 #
b0 $
#330000
b1 !
b110000 "
b1 #
b110000 $
#340000
b10 !
b1101101 "
b10 #
b1101101 $
#350000
b11 !
b1111001 "
b11 #
b1111001 $
#360000
b100 !
b110011 "
b100 #
b110011 $
#370000
b101 !
b1011011 "
b101 #
b1011011 $
#380000
b110 !
b1011111 "
b110 #
b1011111 $
#390000
b111 !
b1110000 "
b111 #
b1110000 $
#400000
b1000 !
b1111111 "
b1000 #
b1111111 $
#410000
b1001 !
b1111011 "
b1001 #
b1111011 $
#420000
b1010 !
b1110111 "
b1010 #
b1110111 $
#430000
b1011 !
b11111 "
b1011 #
b11111 $
#440000
b1100 !
b1001110 "
b1100 #
b1001110 $
#450000
b1101 !
b111101 "
b1101 #
b111101 $
#460000
b1110 !
b1001111 "
b1110 #
b1001111 $
#470000
b1111 !
b1000111 "
b1111 #
b1000111 $
#480000
b0 !
b0 "
b0 #
b0 $
#490000
b1 !
b110000 "
b1 #
b110000 $
#500000
b10 !
b1101101 "
b10 #
b1101101 $
#510000
b11 !
b1111001 "
b11 #
b1111001 $
#520000
b100 !
b110011 "
b100 #
b110011 $
#530000
b101 !
b1011011 "
b101 #
b1011011 $
#540000
b110 !
b1011111 "
b110 #
b1011111 $
#550000
b111 !
b1110000 "
b111 #
b1110000 $
#560000
b1000 !
b1111111 "
b1000 #
b1111111 $
#570000
b1001 !
b1111011 "
b1001 #
b1111011 $
#580000
b1010 !
b1110111 "
b1010 #
b1110111 $
#590000
b1011 !
b11111 "
b1011 #
b11111 $
#600000
b1100 !
b1001110 "
b1100 #
b1001110 $
#610000
b1101 !
b111101 "
b1101 #
b111101 $
#620000
b1110 !
b1001111 "
b1110 #
b1001111 $
#630000
b1111 !
b1000111 "
b1111 #
b1000111 $
#640000
b0 !
b0 "
b0 #
b0 $
#650000
b1 !
b110000 "
b1 #
b110000 $
#660000
b10 !
b1101101 "
b10 #
b1101101 $
#670000
b11 !
b1111001 "
b11 #
b1111001 $
#680000
b100 !
b110011 "
b100 #
b110011 $
#690000
b101 !
b1011011 "
b101 #
b1011011 $
#700000
b110 !
b1011111 "
b110 #
b1011111 $
#710000
b111 !
b1110000 "
b111 #
b1110000 $
#720000
b1000 !
b1111111 "
b1000 #
b1111111 $
#730000
b1001 !
b1111011 "
b1001 #
b1111011 $
#740000
b1010 !
b1110111 "
b1010 #
b1110111 $
#750000
b1011 !
b11111 "
b1011 #
b11111 $
#760000
b1100 !
b1001110 "
b1100 #
b1001110 $
#770000
b1101 !
b111101 "
b1101 #
b111101 $
#780000
b1110 !
b1001111 "
b1110 #
b1001111 $
#790000
b1111 !
b1000111 "
b1111 #
b1000111 $
#800000
b0 !
b0 "
b0 #
b0 $
#810000
b1 !
b110000 "
b1 #
b110000 $
#820000
b10 !
b1101101 "
b10 #
b1101101 $
#830000
b11 !
b1111001 "
b11 #
b1111001 $
#840000
b100 !
b110011 "
b100 #
b110011 $
#850000
b101 !
b1011011 "
b101 #
b1011011 $
#860000
b110 !
b1011111 "
b110 #
b1011111 $
#870000
b111 !
b1110000 "
b111 #
b1110000 $
#880000
b1000 !
b1111111 "
b1000 #
b1111111 $
#890000
b1001 !
b1111011 "
b1001 #
b1111011 $
#900000
b1010 !
b1110111 "
b1010 #
b1110111 $
#910000
b1011 !
b11111 "
b1011 #
b11111 $
#920000
b1100 !
b1001110 "
b1100 #
b1001110 $
#930000
b1101 !
b111101 "
b1101 #
b111101 $
#940000
b1110 !
b1001111 "
b1110 #
b1001111 $
#950000
b1111 !
b1000111 "
b1111 #
b1000111 $
#960000
b0 !
b0 "
b0 #
b0 $
#970000
b1 !
b110000 "
b1 #
b110000 $
#980000
b10 !
b1101101 "
b10 #
b1101101 $
#990000
b11 !
b1111001 "
b11 #
b1111001 $
#1000000
b100 !
b110011 "
b100 #
b110011 $
