Lab1/debounce.v

module debounce(clk, reset, button, button_debounced, button_ON, enabled);
    input clk, reset, button;
    output button_debounced;
    reg button_debounced;
    reg [2:0] FF_wire;
    reg [4:0] counter;
    output wire enabled;
    output wire button_ON;

    // No need to reset cause button has only 2 states
    // after 3 cycles, button_ON will be 0
    always @(posedge reset) begin
        button_debounced = 1'b0;
    end
    
    always @(posedge clk) begin
        FF_wire[0] <= button;
        FF_wire[1] <= FF_wire[0];
        FF_wire[2] <= FF_wire[1];
    end

    assign button_ON = FF_wire[1] & FF_wire[2];
    assign enabled = ~(button_debounced & button_ON);

    always @(posedge clk) begin
        if (enabled) begin
            if (button_ON) begin 
                {button_debounced, counter} <= counter + 1;
            end
            else begin
                button_debounced <= 1'b0;
                counter <= 5'b0;
            end
        end
    end
endmodule

Lab1/debounce_tb.v
`timescale 1ns/10ps

module tb_debounce;
    reg clk;
    reg reset;
    reg button;
    wire button_debounced;
    wire button_ON;
    wire enabled;
    debounce debounce_inst (.clk(clk), .reset(reset), .button(button), .button_debounced(button_debounced), .button_ON(button_ON), .enabled(enabled));

    initial begin
        clk = 1'b0;
        button = 1'b0;
        #10 reset = 1'b1;
        #10 reset = 1'b0;
        #30 button = 1'b1;
        #30 button = 1'b0;
        #30 button = 1'b1;
        #30 button = 1'b0;
        #30 button = 1'b1;
        #30 button = 1'b0;
        #30 button = 1'b1;
        #500 button = 1'b0;
        #30 button = 1'b1;
        #30 button = 1'b0;
        #30 button = 1'b1;
        #30 button = 1'b0;
        #30 button = 1'b1;
        #100 $finish;
    end

    always begin
        #5 clk = ~clk;
    end

endmodule

Lab1/project_1/project_1.sim/sim_1/behav/xsim/tb_debounce.vcd
$date
   Wed Oct 16 02:14:01 2024
$end
$version
  2018.3
$end
$timescale
  1ps
$end
$scope module tb_debounce $end
$var reg 1 ! clk $end
$var reg 1 " reset $end
$var reg 1 # button $end
$var wire 1 $ button_debounced $end
$var wire 1 % button_ON $end
$var wire 1 & enabled $end
$scope module debounce_inst $end
$var wire 1 ' clk $end
$var wire 1 ( reset $end
$var wire 1 ) button $end
$var reg 1 * button_debounced $end
$var reg 3 + FF_wire [2:0] $end
$var reg 5 , counter [4:0] $end
$var wire 1 & enabled $end
$var wire 1 % button_ON $end
$upscope $end
$upscope $end
$enddefinitions $end
#0
$dumpvars
0!
x"
0#
x$
x%
x&
0'
x(
0)
x*
bx +
bx ,
$end
#5000
1!
1'
bx0 +
#10000
0!
1"
0'
1(
#15000
1!
0%
1&
1'
bx00 +
#20000
0!
0"
0'
0(
#25000
1!
0$
0%
1'
0*
b0 +
b0 ,
#30000
0!
0'
#35000
1!
1'
#40000
0!
0'
#45000
1!
1'
#50000
0!
1#
0'
1)
#55000
1!
1'
b1 +
#60000
0!
0'
#65000
1!
0%
1'
b11 +
#70000
0!
0'
#75000
1!
1%
1'
b111 +
#80000
0!
0#
0'
0)
#85000
1!
1'
b110 +
b1 ,
#90000
0!
0'
#95000
1!
0%
1'
b100 +
b10 ,
#100000
0!
0'
#105000
1!
0%
1'
b0 +
b0 ,
#110000
0!
1#
0'
1)
#115000
1!
1'
b1 +
#120000
0!
0'
#125000
1!
0%
1'
b11 +
#130000
0!
0'
#135000
1!
1%
1'
b111 +
#140000
0!
0#
0'
0)
#145000
1!
1'
b110 +
b1 ,
#150000
0!
0'
#155000
1!
0%
1'
b100 +
b10 ,
#160000
0!
0'
#165000
1!
0%
1'
b0 +
b0 ,
#170000
0!
1#
0'
1)
#175000
1!
1'
b1 +
#180000
0!
0'
#185000
1!
0%
1'
b11 +
#190000
0!
0'
#195000
1!
1%
1'
b111 +
#200000
0!
0#
0'
0)
#205000
1!
1'
b110 +
b1 ,
#210000
0!
0'
#215000
1!
0%
1'
b100 +
b10 ,
#220000
0!
0'
#225000
1!
0%
1'
b0 +
b0 ,
#230000
0!
1#
0'
1)
#235000
1!
1'
b1 +
#240000
0!
0'
#245000
1!
0%
1'
b11 +
#250000
0!
0'
#255000
1!
1%
1'
b111 +
#260000
0!
0'
#265000
1!
1'
b1 ,
#270000
0!
0'
#275000
1!
1'
b10 ,
#280000
0!
0'
#285000
1!
1'
b11 ,
#290000
0!
0'
#295000
1!
1'
b100 ,
#300000
0!
0'
#305000
1!
1'
b101 ,
#310000
0!
0'
#315000
1!
1'
b110 ,
#320000
0!
0'
#325000
1!
1'
b111 ,
#330000
0!
0'
#335000
1!
1'
b1000 ,
#340000
0!
0'
#345000
1!
1'
b1001 ,
#350000
0!
0'
#355000
1!
1'
b1010 ,
#360000
0!
0'
#365000
1!
1'
b1011 ,
#370000
0!
0'
#375000
1!
1'
b1100 ,
#380000
0!
0'
#385000
1!
1'
b1101 ,
#390000
0!
0'
#395000
1!
1'
b1110 ,
#400000
0!
0'
#405000
1!
1'
b1111 ,
#410000
0!
0'
#415000
1!
1'
b10000 ,
#420000
0!
0'
#425000
1!
1'
b10001 ,
#430000
0!
0'
#435000
1!
1'
b10010 ,
#440000
0!
0'
#445000
1!
1'
b10011 ,
#450000
0!
0'
#455000
1!
1'
b10100 ,
#460000
0!
0'
#465000
1!
1'
b10101 ,
#470000
0!
0'
#475000
1!
1'
b10110 ,
#480000
0!
0'
#485000
1!
1'
b10111 ,
#490000
0!
0'
#495000
1!
1'
b11000 ,
#500000
0!
0'
#505000
1!
1'
b11001 ,
#510000
0!
0'
#515000
1!
1'
b11010 ,
#520000
0!
0'
#525000
1!
1'
b11011 ,
#530000
0!
0'
#535000
1!
1'
b11100 ,
#540000
0!
0'
#545000
1!
1'
b11101 ,
#550000
0!
0'
#555000
1!
1'
b11110 ,
#560000
0!
0'
#565000
1!
1'
b11111 ,
#570000
0!
0'
#575000
1!
1$
0&
1'
1*
b0 ,
#580000
0!
0'
#585000
1!
1'
#590000
0!
0'
#595000
1!
1'
#600000
0!
0'
#605000
1!
1'
#610000
0!
0'
#615000
1!
1'
#620000
0!
0'
#625000
1!
1'
#630000
0!
0'
#635000
1!
1'
#640000
0!
0'
#645000
1!
1'
#650000
0!
0'
#655000
1!
1'
#660000
0!
0'
#665000
1!
1'
#670000
0!
0'
#675000
1!
1'
#680000
0!
0'
#685000
1!
1'
#690000
0!
0'
#695000
1!
1'
#700000
0!
0'
#705000
1!
1'
#710000
0!
0'
#715000
1!
1'
#720000
0!
0'
#725000
1!
1'
#730000
0!
0#
0'
0)
#735000
1!
1'
b110 +
#740000
0!
0'
#745000
1!
0%
1&
1'
b100 +
#750000
0!
0'
#755000
1!
0$
0%
1'
0*
b0 +
#760000
0!
1#
0'
1)
#765000
1!
1'
b1 +
#770000
0!
0'
#775000
1!
0%
1'
b11 +
#780000
0!
0'
#785000
1!
1%
1'
b111 +
#790000
0!
0#
0'
0)
#795000
1!
1'
b110 +
b1 ,
#800000
0!
0'
#805000
1!
0%
1'
b100 +
b10 ,
#810000
0!
0'
#815000
1!
0%
1'
b0 +
b0 ,
#820000
0!
1#
0'
1)
#825000
1!
1'
b1 +
#830000
0!
0'
#835000
1!
0%
1'
b11 +
#840000
0!
0'
#845000
1!
1%
1'
b111 +
#850000
0!
0#
0'
0)
#855000
1!
1'
b110 +
b1 ,
#860000
0!
0'
#865000
1!
0%
1'
b100 +
b10 ,
#870000
0!
0'
#875000
1!
0%
1'
b0 +
b0 ,
#880000
0!
1#
0'
1)
#885000
1!
1'
b1 +
#890000
0!
0'
#895000
1!
0%
1'
b11 +
#900000
0!
0'
#905000
1!
1%
1'
b111 +
#910000
0!
0'
#915000
1!
1'
b1 ,
#920000
0!
0'
#925000
1!
1'
b10 ,
#930000
0!
0'
#935000
1!
1'
b11 ,
#940000
0!
0'
#945000
1!
1'
b100 ,
#950000
0!
0'
#955000
1!
1'
b101 ,
#960000
0!
0'
#965000
1!
1'
b110 ,
#970000
0!
0'
#975000
1!
1'
b111 ,
